{
  "coach": "Will Hardy",
  "players": [
    {"name": "Collin Sexton", "jersey": "2", "position": "Point Guard"},
    {"name": "Jordan Clarkson", "jersey": "00", "position": "Shooting Guard"},
    {"name": "Lauri Markkanen", "jersey": "23", "position": "Small Forward"},
    {"name": "John Collins", "jersey": "20", "position": "Power Forward"},
    {"name": "Walker Kessler", "jersey": "24", "position": "Center"},
    {"name": "Kris Dunn", "jersey": "11", "position": "Point Guard"},
    {"name": "Taylor Hendricks", "jersey": "0", "position": "Power Forward"},
    {"name": "Omer Yurtseven", "jersey": "77", "position": "Center"}
  ]
} 